django_spiff_workflow/__init__.py
django_spiff_workflow/admin.py
django_spiff_workflow/apps.py
django_spiff_workflow/forms.py
django_spiff_workflow/iterators.py
django_spiff_workflow/mixins.py
django_spiff_workflow/models.py
django_spiff_workflow/registry.py
django_spiff_workflow/runner.py
django_spiff_workflow/script_engine.py
django_spiff_workflow/setup.py
django_spiff_workflow/signals.py
django_spiff_workflow/stores.py
django_spiff_workflow/tests.py
django_spiff_workflow/views.py
django_spiff_workflow/migrations/__init__.py
django_spiff_workflow/parsers/__init__.py
django_spiff_workflow/parsers/parser.py
django_spiff_workflow/serializers/__init__.py
django_spiff_workflow/serializers/data_spec.py
django_spiff_workflow/templates/__init__.py
django_spiff_workflow/templates/manual_task_form.html
django_spiff_workflow/templates/user_task_form.html
django_spiff_workflow/templatetags/__init__.py
django_spiff_workflow/templatetags/workflow_tags.py
django_spiff_workflow-0.1.6.dist-info/LICENSE
django_spiff_workflow-0.1.6.dist-info/METADATA
django_spiff_workflow-0.1.6.dist-info/WHEEL
django_spiff_workflow-0.1.6.dist-info/top_level.txt
django_spiff_workflow-0.1.6.dist-info/RECORD
