Metadata-Version: 2.1
Name: django-spiff-workflow
Version: 0.1.6
Summary: Django integration with spiff workflow library
Home-page: https://github.com/waqqas/django-spiff-workflow
Author: Waqqas Jabbar
Author-email: waqqas.jabbar@egmail.com
License: MIT
Keywords: django,spiff,workflow,bpmn,dmn,bpmn2,business process management
Platform: UNKNOWN
Classifier: Development Status :: 4 - Beta
Classifier: Environment :: Web Environment
Classifier: Framework :: Django
Classifier: Intended Audience :: Developers
Classifier: License :: OSI Approved :: MIT License
Classifier: Operating System :: OS Independent
Classifier: Programming Language :: Python
Classifier: Programming Language :: Python :: 3
Classifier: Programming Language :: Python :: 3.9
Classifier: Programming Language :: Python :: 3.10
Classifier: Programming Language :: Python :: 3.11
Requires-Python: >=3.9
License-File: LICENSE
Requires-Dist: Django >=4.0
Requires-Dist: spiffworkflow >=3.0.0
